Crypto/OTP.py
Crypto/__init__.py
Crypto/Keys/Generate.py
Crypto/Keys/__init__.py
Crypto/Primitives/Conversion.py
Crypto/Primitives/Vernam.py
Crypto/Primitives/__init__.py
KeyFile/__init__.py
KeyFile/core.py
KeyFile/json_encrypt.py
KeyFile/primitives.py
otlib-0.0.2.dist-info/LICENSE
otlib-0.0.2.dist-info/METADATA
otlib-0.0.2.dist-info/WHEEL
otlib-0.0.2.dist-info/top_level.txt
otlib-0.0.2.dist-info/RECORD
